<?xml version="1.0" encoding="utf-8" ?>
<dwsync>
<file name="GLM-11052.JPG" server="68.66.148.106//var/www/bes/" local="128981496550000000" remote="128981496550000000" />
<file name="GLM-12091.JPG" server="68.66.148.106//var/www/bes/" local="128981496550000000" remote="128981496550000000" />
<file name="GLM-12092.JPG" server="68.66.148.106//var/www/bes/" local="128981496560000000" remote="128981496560000000" />
<file name="GLM-12405.JPG" server="68.66.148.106//var/www/bes/" local="128981496560000000" remote="128981496560000000" />
<file name="GLM-13070.JPG" server="68.66.148.106//var/www/bes/" local="128981496560000000" remote="128981496560000000" />
<file name="GLM-13430.JPG" server="68.66.148.106//var/www/bes/" local="128981496560000000" remote="128981496560000000" />
<file name="GLM-13431.JPG" server="68.66.148.106//var/www/bes/" local="128981496570000000" remote="128981496570000000" />
<file name="GLM-13440.JPG" server="68.66.148.106//var/www/bes/" local="128981496570000000" remote="128981496570000000" />
<file name="GLM-16300.JPG" server="68.66.148.106//var/www/bes/" local="128981496570000000" remote="128981496570000000" />
<file name="GLM-16330.JPG" server="68.66.148.106//var/www/bes/" local="128981496570000000" remote="128981496570000000" />
<file name="GLM-16340.JPG" server="68.66.148.106//var/www/bes/" local="128981496580000000" remote="128981496580000000" />
<file name="GLM-21111.JPG" server="68.66.148.106//var/www/bes/" local="128981496580000000" remote="128981496580000000" />
<file name="GLM-21541.JPG" server="68.66.148.106//var/www/bes/" local="128981496580000000" remote="128981496580000000" />
<file name="GLM-21586.JPG" server="68.66.148.106//var/www/bes/" local="128981496580000000" remote="128981496580000000" />
<file name="GLM-21611.JPG" server="68.66.148.106//var/www/bes/" local="128981496590000000" remote="128981496590000000" />
<file name="GLM-21642.JPG" server="68.66.148.106//var/www/bes/" local="128981496590000000" remote="128981496590000000" />
<file name="GLM-21715.JPG" server="68.66.148.106//var/www/bes/" local="128981496600000000" remote="128981496600000000" />
<file name="GLM-21850.JPG" server="68.66.148.106//var/www/bes/" local="128981496600000000" remote="128981496600000000" />
<file name="GLM-22150.JPG" server="68.66.148.106//var/www/bes/" local="128981496600000000" remote="128981496600000000" />
<file name="GLM-22186.JPG" server="68.66.148.106//var/www/bes/" local="128981496600000000" remote="128981496600000000" />
<file name="GLM-22189.JPG" server="68.66.148.106//var/www/bes/" local="128981496610000000" remote="128981496610000000" />
<file name="GLM-22200.JPG" server="68.66.148.106//var/www/bes/" local="128981496610000000" remote="128981496610000000" />
<file name="GLM-22221.JPG" server="68.66.148.106//var/www/bes/" local="128981496620000000" remote="128981496620000000" />
<file name="GLM-22225.JPG" server="68.66.148.106//var/www/bes/" local="128981496620000000" remote="128981496620000000" />
<file name="GLM-22230.JPG" server="68.66.148.106//var/www/bes/" local="128981496620000000" remote="128981496620000000" />
<file name="GLM-22235.JPG" server="68.66.148.106//var/www/bes/" local="128981496630000000" remote="128981496630000000" />
<file name="GLM-22250.JPG" server="68.66.148.106//var/www/bes/" local="128981496630000000" remote="128981496630000000" />
<file name="GLM-22252.JPG" server="68.66.148.106//var/www/bes/" local="128981496630000000" remote="128981496630000000" />
<file name="GLM-22310.JPG" server="68.66.148.106//var/www/bes/" local="128981496630000000" remote="128981496630000000" />
<file name="GLM-22340.JPG" server="68.66.148.106//var/www/bes/" local="128981496640000000" remote="128981496640000000" />
<file name="GLM-22387.JPG" server="68.66.148.106//var/www/bes/" local="128981496640000000" remote="128981496640000000" />
<file name="GLM-22410.JPG" server="68.66.148.106//var/www/bes/" local="128981496640000000" remote="128981496640000000" />
<file name="GLM-22411.JPG" server="68.66.148.106//var/www/bes/" local="128981496640000000" remote="128981496640000000" />
<file name="GLM-22600.JPG" server="68.66.148.106//var/www/bes/" local="128981496650000000" remote="128981496650000000" />
<file name="GLM-22622.JPG" server="68.66.148.106//var/www/bes/" local="128981496650000000" remote="128981496650000000" />
<file name="GLM-22623.JPG" server="68.66.148.106//var/www/bes/" local="128981496660000000" remote="128981496660000000" />
<file name="GLM-22625.JPG" server="68.66.148.106//var/www/bes/" local="128981496660000000" remote="128981496660000000" />
<file name="GLM-22630.JPG" server="68.66.148.106//var/www/bes/" local="128981496660000000" remote="128981496660000000" />
<file name="GLM-22631.JPG" server="68.66.148.106//var/www/bes/" local="128981496660000000" remote="128981496660000000" />
<file name="GLM-22633.JPG" server="68.66.148.106//var/www/bes/" local="128981496670000000" remote="128981496670000000" />
<file name="GLM-22860.JPG" server="68.66.148.106//var/www/bes/" local="128981496670000000" remote="128981496670000000" />
<file name="GLM-22870.JPG" server="68.66.148.106//var/www/bes/" local="128981496680000000" remote="128981496680000000" />
<file name="GLM-22880.JPG" server="68.66.148.106//var/www/bes/" local="128981496680000000" remote="128981496680000000" />
<file name="GLM-23010.JPG" server="68.66.148.106//var/www/bes/" local="128981496680000000" remote="128981496680000000" />
<file name="GLM-23011.JPG" server="68.66.148.106//var/www/bes/" local="128981496680000000" remote="128981496680000000" />
<file name="GLM-23020.JPG" server="68.66.148.106//var/www/bes/" local="128981496690000000" remote="128981496690000000" />
<file name="GLM-23040.JPG" server="68.66.148.106//var/www/bes/" local="128981496690000000" remote="128981496690000000" />
<file name="GLM-23100.JPG" server="68.66.148.106//var/www/bes/" local="128981496690000000" remote="128981496690000000" />
<file name="GLM-23111.JPG" server="68.66.148.106//var/www/bes/" local="128981496690000000" remote="128981496690000000" />
<file name="GLM-23120.JPG" server="68.66.148.106//var/www/bes/" local="128981496700000000" remote="128981496700000000" />
<file name="GLM-23130.JPG" server="68.66.148.106//var/www/bes/" local="128981496700000000" remote="128981496700000000" />
<file name="GLM-23150.JPG" server="68.66.148.106//var/www/bes/" local="128981496700000000" remote="128981496700000000" />
<file name="GLM-23160.JPG" server="68.66.148.106//var/www/bes/" local="128981496710000000" remote="128981496710000000" />
<file name="GLM-23310.JPG" server="68.66.148.106//var/www/bes/" local="128981496710000000" remote="128981496710000000" />
<file name="GLM-24930.JPG" server="68.66.148.106//var/www/bes/" local="128981496720000000" remote="128981496720000000" />
<file name="GLM-27730.JPG" server="68.66.148.106//var/www/bes/" local="128981496720000000" remote="128981496720000000" />
<file name="GLM-27770.JPG" server="68.66.148.106//var/www/bes/" local="128981496720000000" remote="128981496720000000" />
<file name="GLM-27850.JPG" server="68.66.148.106//var/www/bes/" local="128981496730000000" remote="128981496730000000" />
<file name="GLM-27900.JPG" server="68.66.148.106//var/www/bes/" local="128981496730000000" remote="128981496730000000" />
<file name="GLM-280.JPG" server="68.66.148.106//var/www/bes/" local="128981496740000000" remote="128981496740000000" />
<file name="GLM-28020.JPG" server="68.66.148.106//var/www/bes/" local="128981496730000000" remote="128981496730000000" />
<file name="GLM-28317.JPG" server="68.66.148.106//var/www/bes/" local="128981496740000000" remote="128981496740000000" />
<file name="GLM-28318.JPG" server="68.66.148.106//var/www/bes/" local="128981496750000000" remote="128981496750000000" />
<file name="GLM-28406.JPG" server="68.66.148.106//var/www/bes/" local="128981496750000000" remote="128981496750000000" />
<file name="GLM-28460.JPG" server="68.66.148.106//var/www/bes/" local="128981496750000000" remote="128981496750000000" />
<file name="GLM-28481.JPG" server="68.66.148.106//var/www/bes/" local="128981496750000000" remote="128981496750000000" />
<file name="GLM-28820.JPG" server="68.66.148.106//var/www/bes/" local="128981496760000000" remote="128981496760000000" />
<file name="GLM-29910.JPG" server="68.66.148.106//var/www/bes/" local="128981496760000000" remote="128981496760000000" />
<file name="GLM-29920.JPG" server="68.66.148.106//var/www/bes/" local="128981496770000000" remote="128981496770000000" />
<file name="GLM-31171.JPG" server="68.66.148.106//var/www/bes/" local="128981496770000000" remote="128981496770000000" />
<file name="GLM-32580.JPG" server="68.66.148.106//var/www/bes/" local="128981496780000000" remote="128981496780000000" />
<file name="GLM-32970.JPG" server="68.66.148.106//var/www/bes/" local="128981496780000000" remote="128981496780000000" />
<file name="GLM-33040.JPG" server="68.66.148.106//var/www/bes/" local="128981496780000000" remote="128981496780000000" />
<file name="GLM-33770.JPG" server="68.66.148.106//var/www/bes/" local="128981496780000000" remote="128981496780000000" />
<file name="GLM-33790.JPG" server="68.66.148.106//var/www/bes/" local="128981496790000000" remote="128981496790000000" />
<file name="GLM-33800.JPG" server="68.66.148.106//var/www/bes/" local="128981496790000000" remote="128981496790000000" />
<file name="GLM-33810.JPG" server="68.66.148.106//var/www/bes/" local="128981496790000000" remote="128981496790000000" />
<file name="GLM-34771.JPG" server="68.66.148.106//var/www/bes/" local="128981496790000000" remote="128981496790000000" />
<file name="GLM-35080.JPG" server="68.66.148.106//var/www/bes/" local="128981496800000000" remote="128981496800000000" />
<file name="GLM-35160.JPG" server="68.66.148.106//var/www/bes/" local="128981496800000000" remote="128981496800000000" />
<file name="GLM-35170.JPG" server="68.66.148.106//var/www/bes/" local="128981496800000000" remote="128981496800000000" />
<file name="GLM-37100.JPG" server="68.66.148.106//var/www/bes/" local="128981496810000000" remote="128981496810000000" />
<file name="GLM-38631.JPG" server="68.66.148.106//var/www/bes/" local="128981496810000000" remote="128981496810000000" />
<file name="GLM-39630.JPG" server="68.66.148.106//var/www/bes/" local="128981496810000000" remote="128981496810000000" />
<file name="GLM-39631.JPG" server="68.66.148.106//var/www/bes/" local="128981496820000000" remote="128981496820000000" />
<file name="GLM-39820.JPG" server="68.66.148.106//var/www/bes/" local="128981496820000000" remote="128981496820000000" />
<file name="GLM-71470.JPG" server="68.66.148.106//var/www/bes/" local="128981496820000000" remote="128981496820000000" />
<file name="GLM-71480.JPG" server="68.66.148.106//var/www/bes/" local="128981496830000000" remote="128981496830000000" />
<file name="GLM-71490.JPG" server="68.66.148.106//var/www/bes/" local="128981496830000000" remote="128981496830000000" />
<file name="GLM-71560.JPG" server="68.66.148.106//var/www/bes/" local="128981496830000000" remote="128981496830000000" />
<file name="GLM-71720.JPG" server="68.66.148.106//var/www/bes/" local="128981496830000000" remote="128981496830000000" />
<file name="GLM-71730.JPG" server="68.66.148.106//var/www/bes/" local="128981496840000000" remote="128981496840000000" />
<file name="GLM-71800.JPG" server="68.66.148.106//var/www/bes/" local="128981496840000000" remote="128981496840000000" />
<file name="GLM-72116.JPG" server="68.66.148.106//var/www/bes/" local="128981496850000000" remote="128981496850000000" />
<file name="GLM-72430.JPG" server="68.66.148.106//var/www/bes/" local="128981496850000000" remote="128981496850000000" />
<file name="GLM-72600.JPG" server="68.66.148.106//var/www/bes/" local="128981496850000000" remote="128981496850000000" />
<file name="GLM-72660.JPG" server="68.66.148.106//var/www/bes/" local="128981496850000000" remote="128981496850000000" />
<file name="GLM-72680.JPG" server="68.66.148.106//var/www/bes/" local="128981496860000000" remote="128981496860000000" />
<file name="GLM-72690.JPG" server="68.66.148.106//var/www/bes/" local="128981496860000000" remote="128981496860000000" />
<file name="GLM-72700.JPG" server="68.66.148.106//var/www/bes/" local="128981496870000000" remote="128981496870000000" />
<file name="GLM-73010.JPG" server="68.66.148.106//var/www/bes/" local="128981496860000000" remote="128981496860000000" />
<file name="GLM-73020.JPG" server="68.66.148.106//var/www/bes/" local="128981496870000000" remote="128981496870000000" />
<file name="GLM-76068.JPG" server="68.66.148.106//var/www/bes/" local="128981496870000000" remote="128981496870000000" />
<file name="GLM-76088.JPG" server="68.66.148.106//var/www/bes/" local="128981496880000000" remote="128981496880000000" />
<file name="GLM-76101.JPG" server="68.66.148.106//var/www/bes/" local="128981496880000000" remote="128981496880000000" />
<file name="GLM-76102.JPG" server="68.66.148.106//var/www/bes/" local="128981496880000000" remote="128981496880000000" />
<file name="GLM-76103.JPG" server="68.66.148.106//var/www/bes/" local="128981496890000000" remote="128981496890000000" />
<file name="GLM-76104.JPG" server="68.66.148.106//var/www/bes/" local="128981496890000000" remote="128981496890000000" />
<file name="GLM-76108.JPG" server="68.66.148.106//var/www/bes/" local="128981496890000000" remote="128981496890000000" />
<file name="GLM-76120.JPG" server="68.66.148.106//var/www/bes/" local="128981496900000000" remote="128981496900000000" />
<file name="GLM-80140.JPG" server="68.66.148.106//var/www/bes/" local="128981496900000000" remote="128981496900000000" />
<file name="GLM-80180.JPG" server="68.66.148.106//var/www/bes/" local="128981496900000000" remote="128981496900000000" />
<file name="GLM-81180.JPG" server="68.66.148.106//var/www/bes/" local="128981496900000000" remote="128981496900000000" />
<file name="GLM-82150.JPG" server="68.66.148.106//var/www/bes/" local="128981496910000000" remote="128981496910000000" />
<file name="GLM-82430.JPG" server="68.66.148.106//var/www/bes/" local="128981496910000000" remote="128981496910000000" />
<file name="GLM-86610.JPG" server="68.66.148.106//var/www/bes/" local="128981496910000000" remote="128981496910000000" />
<file name="GLM-86620.JPG" server="68.66.148.106//var/www/bes/" local="128981496920000000" remote="128981496920000000" />
<file name="GLM-86700.JPG" server="68.66.148.106//var/www/bes/" local="128981496920000000" remote="128981496920000000" />
<file name="GLM-86710.JPG" server="68.66.148.106//var/www/bes/" local="128981496920000000" remote="128981496920000000" />
<file name="GLM-86720.JPG" server="68.66.148.106//var/www/bes/" local="128981496930000000" remote="128981496930000000" />
<file name="GLM-87100.JPG" server="68.66.148.106//var/www/bes/" local="128981496930000000" remote="128981496930000000" />
<file name="GLM-87620.JPG" server="68.66.148.106//var/www/bes/" local="128981496930000000" remote="128981496930000000" />
<file name="GLM-87630.JPG" server="68.66.148.106//var/www/bes/" local="128981496930000000" remote="128981496930000000" />
<file name="GLM-87650.JPG" server="68.66.148.106//var/www/bes/" local="128981496940000000" remote="128981496940000000" />
<file name="GLM-87651.JPG" server="68.66.148.106//var/www/bes/" local="128981496940000000" remote="128981496940000000" />
<file name="GLM-87654.JPG" server="68.66.148.106//var/www/bes/" local="128981496950000000" remote="128981496950000000" />
<file name="GLM-87655.JPG" server="68.66.148.106//var/www/bes/" local="128981496950000000" remote="128981496950000000" />
<file name="GLM-87656.JPG" server="68.66.148.106//var/www/bes/" local="128981496960000000" remote="128981496960000000" />
<file name="GLM-87660.JPG" server="68.66.148.106//var/www/bes/" local="128981496960000000" remote="128981496960000000" />
<file name="GLM-87700.JPG" server="68.66.148.106//var/www/bes/" local="128981496960000000" remote="128981496960000000" />
<file name="GLM-87710.JPG" server="68.66.148.106//var/www/bes/" local="128981496960000000" remote="128981496960000000" />
<file name="GLM-87730.JPG" server="68.66.148.106//var/www/bes/" local="128981496970000000" remote="128981496970000000" />
<file name="GLM-87740.JPG" server="68.66.148.106//var/www/bes/" local="128981496970000000" remote="128981496970000000" />
<file name="GLM-87750.JPG" server="68.66.148.106//var/www/bes/" local="128981496980000000" remote="128981496980000000" />
<file name="GLM-89010.JPG" server="68.66.148.106//var/www/bes/" local="128981496980000000" remote="128981496980000000" />
<file name="GLM-89020.JPG" server="68.66.148.106//var/www/bes/" local="128981496980000000" remote="128981496980000000" />
<file name="GLM-89030.JPG" server="68.66.148.106//var/www/bes/" local="128981496990000000" remote="128981496990000000" />
<file name="GLM-89190.JPG" server="68.66.148.106//var/www/bes/" local="128981496990000000" remote="128981496990000000" />
<file name="GLM-89200.JPG" server="68.66.148.106//var/www/bes/" local="128981497000000000" remote="128981497000000000" />
<file name="GLM-89210.JPG" server="68.66.148.106//var/www/bes/" local="128981497000000000" remote="128981497000000000" />
<file name="GLM-89220.JPG" server="68.66.148.106//var/www/bes/" local="128981497000000000" remote="128981497000000000" />
<file name="GLM-89222.JPG" server="68.66.148.106//var/www/bes/" local="128981497000000000" remote="128981497000000000" />
<file name="GLM-89224.JPG" server="68.66.148.106//var/www/bes/" local="128981497010000000" remote="128981497010000000" />
<file name="GLM-89230.JPG" server="68.66.148.106//var/www/bes/" local="128981497010000000" remote="128981497010000000" />
<file name="GLM-89510.JPG" server="68.66.148.106//var/www/bes/" local="128981497010000000" remote="128981497010000000" />
<file name="GLM-89520.JPG" server="68.66.148.106//var/www/bes/" local="128981497010000000" remote="128981497010000000" />
<file name="GLM-89530.JPG" server="68.66.148.106//var/www/bes/" local="128981497020000000" remote="128981497020000000" />
<file name="GLM-89540.JPG" server="68.66.148.106//var/www/bes/" local="128981497020000000" remote="128981497020000000" />
<file name="GLM-89550.JPG" server="68.66.148.106//var/www/bes/" local="128981497020000000" remote="128981497020000000" />
<file name="GLM-89560.JPG" server="68.66.148.106//var/www/bes/" local="128981497030000000" remote="128981497030000000" />
<file name="GLM-89595.JPG" server="68.66.148.106//var/www/bes/" local="128981497030000000" remote="128981497030000000" />
<file name="GLM-89610.JPG" server="68.66.148.106//var/www/bes/" local="128981497030000000" remote="128981497030000000" />
<file name="GLM-89611.JPG" server="68.66.148.106//var/www/bes/" local="128981497040000000" remote="128981497040000000" />
<file name="GLM-89620.JPG" server="68.66.148.106//var/www/bes/" local="128981497040000000" remote="128981497040000000" />
<file name="GLM-89760.JPG" server="68.66.148.106//var/www/bes/" local="128981497040000000" remote="128981497040000000" />
<file name="GLM-89950.JPG" server="68.66.148.106//var/www/bes/" local="128981497040000000" remote="128981497040000000" />
<file name="Thumbs.db" server="68.66.148.106//var/www/bes/" local="128981497120000000" remote="128981497120000000" />
</dwsync>